ms_recognizers_text/__init__.py
ms_recognizers_text/culture.py
ms_recognizers_text/extractor.py
ms_recognizers_text/meta_data.py
ms_recognizers_text/model.py
ms_recognizers_text/parser.py
ms_recognizers_text/recognizer.py
ms_recognizers_text/utilities.py
ms_recognizers_text/matcher/__init__.py
ms_recognizers_text/matcher/aa_node.py
ms_recognizers_text/matcher/abstract_matcher.py
ms_recognizers_text/matcher/ac_automaton.py
ms_recognizers_text/matcher/match_result.py
ms_recognizers_text/matcher/match_strategy.py
ms_recognizers_text/matcher/matcher.py
ms_recognizers_text/matcher/node.py
ms_recognizers_text/matcher/number_with_unit_tokenizer.py
ms_recognizers_text/matcher/simple_tokenizer.py
ms_recognizers_text/matcher/string_matcher.py
ms_recognizers_text/matcher/token.py
ms_recognizers_text/matcher/tokenizer.py
ms_recognizers_text/matcher/trie_tree.py
ms_recognizers_text-1.0.1.dist-info/METADATA
ms_recognizers_text-1.0.1.dist-info/WHEEL
ms_recognizers_text-1.0.1.dist-info/top_level.txt
ms_recognizers_text-1.0.1.dist-info/RECORD
